satellite_insight_extractor/__init__.py
satellite_insight_extractor/main.py
satellite_insight_extractor/prompts.py
satellite_insight_extractor-2025.12.21080509.dist-info/METADATA
satellite_insight_extractor-2025.12.21080509.dist-info/WHEEL
satellite_insight_extractor-2025.12.21080509.dist-info/top_level.txt
satellite_insight_extractor-2025.12.21080509.dist-info/RECORD
