Metadata-Version: 2.4
Name: satellite-insight-extractor
Version: 2025.12.21080509
Summary: A new package designed to streamline the extraction of structured insights from brief, domain-specific reports. It receives a short text input describing recent events—such as satellite incidents—and 
Author-email: satellite-insight-extractor <hi@eugene.plus>
License: MIT
Project-URL: Homepage, https://github.com/chigwell/satellite-insight-extractor
Requires-Python: >=3.9
Requires-Dist: langchain-llm7>=0.0.0
Requires-Dist: llmatch-messages>=0.0.0
Requires-Dist: langchain-core>=0.3.0
